README
setup.py
datastore_reader/__init__.py
datastore_reader/_datastore_reader.py
datastore_reader.egg-info/PKG-INFO
datastore_reader.egg-info/SOURCES.txt
datastore_reader.egg-info/dependency_links.txt
datastore_reader.egg-info/entry_points.txt
datastore_reader.egg-info/not-zip-safe
datastore_reader.egg-info/requires.txt
datastore_reader.egg-info/top_level.txt
datastore_reader/utils/__init__.py
datastore_reader/utils/_csv.py
datastore_reader/utils/config.py