Metadata-Version: 1.0
Name: datastore-reader
Version: 0.1
Summary: Sugar DS reader for backup analysis
Home-page: UNKNOWN
Author: Florent Pigout
Author-email: florent.pigout@gmail.com
License: MIT
Platform: UNKNOWN
